Workbook

Sheet Resumen Ejecutivo
A1: Simulación de Costos, Beneficios y ROI
A2: Sistema de Detección de Fraudes con IA · Empresa mediana (México) · Cifras en MXN · Horizonte: 3 años
A4: Descripción del proyecto
A5: Implementación de un sistema de inteligencia artificial para detectar transacciones fraudulentas en tiempo real. El modelo de machine learning analiza patrones transaccionales para reducir pérdidas por fraude, disminuir la revisión manual y mejorar la experiencia del cliente al reducir falsos positivos. Este tablero resume la viabilidad económica del proyecto.
A9: Indicadores clave del proyecto
A10: Indicador | B10: Valor | C10: Lectura
A11: Inversión inicial (Año 0) | B11: ='ROI y Payback'!$B$4 -> 6400000 | C11: Desembolso único para construir el sistema
A12: Costo recurrente anual (OPEX) | B12: ='ROI y Payback'!$B$5 -> 3100000 | C12: Operación y mantenimiento por año
A13: Costos totales (3 años) | B13: ='ROI y Payback'!$B$24 -> 15700000 | C13: Inversión + operación a 3 años
A14: Beneficios totales (3 años) | B14: ='ROI y Payback'!$B$25 -> 30525000 | C14: Ahorros y recuperaciones a 3 años
A15: Beneficio neto (3 años) | B15: ='ROI y Payback'!$B$26 -> 14825000 | C15: Valor económico generado
A16: ROI (3 años) | B16: ='ROI y Payback'!$B$27 -> 0.94426752 | C16: Por cada $1 invertido se recupera ese % adicional
A17: Periodo de recuperación (Payback) | B17: ='ROI y Payback'!$B$28 -> 1.146875 | C17: Años para recuperar la inversión
A18: Valor Presente Neto (VPN, 12%) | B18: ='ROI y Payback'!$B$30 -> 10336972 | C18: Valor del proyecto descontado a hoy
A20: Interpretación y conclusión
A21: El proyecto es económicamente viable: genera un ROI positivo a 3 años, un VPN positivo a una tasa de descuento del 12% y recupera la inversión en poco más de un año. Estos resultados respaldan la decisión de inversión, siempre que se gestionen activamente los riesgos de sesgo, ética, explicabilidad y mantenimiento descritos en el mapa de riesgos y en el plan de mitigación.
A25: Leyenda de color: azul = dato de entrada (modificable) · negro = fórmula · verde = vínculo entre hojas.

Sheet Costos
A1: Costos del Proyecto — Sistema de Detección de Fraudes con IA (MXN)
A3: A. Costos tangibles: inversión inicial (CAPEX, Año 0) y costos recurrentes (OPEX, anual)
A4: Concepto | B4: Categoría | C4: Tipo | D4: Inversión inicial (Año 0) | E4: Costo recurrente (anual) | F4: Notas / Supuesto
A5: Configuración de infraestructura cloud (cómputo/GPU) | B5: Infraestructura | C5: Tangible | D5: 650000 | F5: Entorno de entrenamiento y arquitectura del modelo
A6: Hardware / edge para inferencia de baja latencia | B6: Infraestructura | C6: Tangible | D6: 350000 | F6: Componentes para respuesta en tiempo real
A7: Adquisición e integración de fuentes de datos | B7: Datos | C7: Tangible | D7: 400000 | F7: Conexión a sistemas transaccionales y externos
A8: Limpieza, etiquetado y curado del dataset histórico | B8: Datos | C8: Tangible | D8: 700000 | F8: Preparación de datos de fraude/no fraude
A9: Construcción de data lake y pipelines de datos | B9: Datos | C9: Tangible | D9: 500000 | F9: Ingesta y procesamiento continuo
A10: Científico de datos senior (líder, fase de desarrollo) | B10: Talento | C10: Tangible | D10: 900000 | F10: ~6-8 meses de desarrollo
A11: Dos ingenieros de Machine Learning (desarrollo) | B11: Talento | C11: Tangible | D11: 1200000 | F11: Construcción y validación del modelo
A12: Ingeniero de datos (desarrollo) | B12: Talento | C12: Tangible | D12: 500000 | F12: Arquitectura de datos
A13: Project manager (dedicación parcial) | B13: Talento | C13: Tangible | D13: 300000 | F13: Coordinación del proyecto
A14: Plataforma MLOps (implementación) | B14: Herramientas | C14: Tangible | D14: 250000 | F14: Despliegue, versionado y CI/CD del modelo
A15: Herramientas de explicabilidad y monitoreo de sesgo (setup) | B15: Herramientas | C15: Tangible | D15: 150000 | F15: SHAP/LIME, paneles de equidad
A16: Consultoría legal, ética y cumplimiento (CNBV, LFPDPPP) | B16: Cumplimiento | C16: Tangible | D16: 300000 | F16: Marco regulatorio y protección de datos
A17: Capacitación inicial de equipo y usuarios | B17: Gestión del cambio | C17: Tangible | D17: 200000 | F17: Adopción y uso responsable
A18: Cómputo cloud para inferencia y almacenamiento | B18: Infraestructura | C18: Tangible | E18: 900000 | F18: Operación continua del sistema
A19: Actualización y enriquecimiento continuo de datos | B19: Datos | C19: Tangible | E19: 300000 | F19: Datos frescos para reentrenamiento
A20: Ingeniero de ML (mantenimiento y reentrenamiento, 1 FTE) | B20: Talento | C20: Tangible | E20: 700000 | F20: Evita degradación del modelo
A21: Analista de MLOps y monitoreo (0.5 FTE) | B21: Talento | C21: Tangible | E21: 350000 | F21: Vigilancia de desempeño y drift
A22: Científico de datos (soporte parcial) | B22: Talento | C22: Tangible | E22: 250000 | F22: Mejoras y ajustes del modelo
A23: Licencias anuales (MLOps, explicabilidad, monitoreo) | B23: Herramientas | C23: Tangible | E23: 400000 | F23: Suscripciones de software
A24: Auditoría de sesgo, ética y cumplimiento | B24: Cumplimiento | C24: Tangible | E24: 200000 | F24: Revisión periódica independiente
A25: TOTAL COSTOS TANGIBLES | D25: =SUM(D5:D24) -> 6400000 | E25: =SUM(E5:E24) -> 3100000
A27: B. Costos intangibles (gestión cualitativa — criterio conservador: no se monetizan en el flujo base)
A28: Concepto | B28: Categoría | C28: Tipo | D28: Impacto estimado | E28: Notas
A29: Curva de aprendizaje y baja temporal de productividad | B29: Organizacional | C29: Intangible | D29: Medio | E29: Afecta las primeras semanas; mitigable con capacitación
A30: Resistencia al cambio del equipo de prevención de fraude | B30: Organizacional | C30: Intangible | D30: Medio | E30: Riesgo de adopción; requiere gestión del cambio
A31: Riesgo reputacional durante el despliegue inicial | B31: Reputacional | C31: Intangible | D31: Alto | E31: Errores tempranos del modelo pueden afectar la imagen
A32: Costo de oportunidad de la dirección y especialistas | B32: Estratégico | C32: Intangible | D32: Medio | E32: Tiempo dedicado al proyecto vs. otras iniciativas
A33: Nota: los costos intangibles se documentan y gestionan cualitativamente. Por criterio conservador no se monetizan en el flujo de caja base; su tratamiento se aborda en el plan de mitigación de riesgos (Word).

Sheet Beneficios
A1: Beneficios del Proyecto — Sistema de Detección de Fraudes con IA (MXN)
A3: A. Beneficios tangibles (anuales, a plena capacidad operativa)
A4: Concepto | B4: Categoría | C4: Tipo | D4: Beneficio anual | E4: Notas / Supuesto
A5: Reducción de pérdidas por fraude (detección temprana) | B5: Operativo | C5: Tangible | D5: 7000000 | E5: ≈40% sobre pérdidas base estimadas de ~$17.5 M anuales
A6: Reducción de costos por revisión manual de alertas | B6: Operativo | C6: Tangible | D6: 1800000 | E6: Automatización del triage; menor carga del equipo
A7: Recuperación de ventas por menor tasa de falsos positivos | B7: Comercial | C7: Tangible | D7: 1400000 | E7: Menos transacciones legítimas rechazadas
A8: Reducción de chargebacks y costos de disputa | B8: Financiero | C8: Tangible | D8: 900000 | E8: Menos contracargos y gestión de disputas
A9: TOTAL BENEFICIOS TANGIBLES (anual) | D9: =SUM(D5:D8) -> 11100000
A11: B. Beneficios intangibles (cualitativos — criterio conservador: no monetizados en el ROI)
A12: Concepto | B12: Categoría | C12: Tipo | D12: Impacto | E12: Notas
A13: Mayor confianza y retención de clientes | B13: Cliente | C13: Intangible | D13: Alto | E13: Mejor experiencia y menor fricción en pagos
A14: Fortalecimiento de marca y reputación | B14: Reputacional | C14: Intangible | D14: Alto | E14: Posicionamiento como empresa segura y confiable
A15: Mejor cumplimiento regulatorio (menor riesgo de multas) | B15: Cumplimiento | C15: Intangible | D15: Alto | E15: Alineación con CNBV y LFPDPPP
A16: Capacidades analíticas y decisiones basadas en datos | B16: Estratégico | C16: Intangible | D16: Medio | E16: Reutilización de la infraestructura de datos
A17: Nota: por criterio conservador, los beneficios intangibles no se incluyen en el cálculo del ROI; refuerzan cualitativamente la justificación estratégica del proyecto.

Sheet ROI y Payback
A1: Análisis de ROI y Periodo de Recuperación (Payback) — MXN
A3: Supuestos del modelo
A4: Inversión inicial (Año 0) | B4: =Costos!D25 -> 6400000
A5: Costo recurrente anual (OPEX) | B5: =Costos!E25 -> 3100000
A6: Beneficio anual a plena capacidad | B6: =Beneficios!D9 -> 11100000
A7: Rampa de adopción — Año 1 | B7: 0.75
A8: Rampa de adopción — Año 2 | B8: 1
A9: Rampa de adopción — Año 3 | B9: 1
A10: Tasa de descuento (para VPN) | B10: 0.12
A12: Flujo de caja del proyecto (MXN)
A13: Concepto | B13: Año 0 | C13: Año 1 | D13: Año 2 | E13: Año 3
A14: Inversión inicial | B14: =-$B$4 -> -6400000 | C14: 0 | D14: 0 | E14: 0
A15: Beneficios | B15: 0 | C15: =$B$6*$B$7 -> 8325000 | D15: =$B$6*$B$8 -> 11100000 | E15: =$B$6*$B$9 -> 11100000
A16: Costos recurrentes (OPEX) | B16: 0 | C16: =-$B$5 -> -3100000 | D16: =-$B$5 -> -3100000 | E16: =-$B$5 -> -3100000
A17: Flujo neto del año | B17: =SUM(B14:B16) -> -6400000 | C17: =SUM(C14:C16) -> 5225000 | D17: =SUM(D14:D16) -> 8000000 | E17: =SUM(E14:E16) -> 8000000
A18: Flujo de caja acumulado | B18: =B17 -> -6400000 | C18: =B18+C17 -> -1175000 | D18: =C18+D17 -> 6825000 | E18: =D18+E17 -> 14825000
A19: Factor de descuento | B19: =1/(1+$B$10)^0 -> 1 | C19: =1/(1+$B$10)^1 -> 0.89285714 | D19: =1/(1+$B$10)^2 -> 0.79719388 | E19: =1/(1+$B$10)^3 -> 0.71178025
A20: Flujo descontado | B20: =B17*B19 -> -6400000 | C20: =C17*C19 -> 4665178.6 | D20: =D17*D19 -> 6377551 | E20: =E17*E19 -> 5694242
A22: Resultados del análisis
A23: Indicador | B23: Valor | C23: Cómo se calcula
A24: Costos totales (3 años) | B24: =-(SUM(B14:E14)+SUM(B16:E16)) -> 15700000 | C24: Inversión inicial + 3 años de OPEX
A25: Beneficios totales (3 años) | B25: =SUM(B15:E15) -> 30525000 | C25: Suma de beneficios con rampa de adopción
A26: Beneficio neto (3 años) | B26: =B25-B24 -> 14825000 | C26: Beneficios totales − Costos totales
A27: ROI (3 años) | B27: =B26/B24 -> 0.94426752 | C27: Beneficio neto / Costos totales
A28: Payback (años) | B28: =1+ABS(C18)/D17 -> 1.146875 | C28: Recuperación durante el Año 2: 1 + |acum. Año 1| / flujo neto Año 2
A29: Payback (meses) | B29: =B28*12 -> 13.7625 | C29: Equivalente en meses (≈ 1 año y 2 meses)
A30: Valor Presente Neto (VPN, 12%) | B30: =SUM(B20:E20) -> 10336972 | C30: Suma de los flujos descontados
A31: Tasa Interna de Retorno (TIR) | B31: =IRR(B17:E17) -> 0.85415946 | C31: Rendimiento que iguala el VPN a cero
